secureaiml-0.1.3.dist-info/licenses/LICENSE
secureml/__init__.py
secureml/api/__init__.py
secureml/api/advanced.py
secureml/api/simple.py
secureml/cli/__init__.py
secureml/cli/main.py
secureml/core/__init__.py
secureml/core/compliance.py
secureml/core/enterprise.py
secureml/core/fingerprint.py
secureml/core/model_detector.py
secureml/core/openssf_wrapper.py
secureml/core/watermark.py
secureml/handlers/__init__.py
secureml/handlers/base_handler.py
secureml/integrations/__init__.py
secureml/security/__init__.py
secureml/utils/__init__.py
secureml/utils/config.py
secureml/utils/exceptions.py
secureml/utils/logging.py
secureaiml-0.1.3.dist-info/METADATA
secureaiml-0.1.3.dist-info/WHEEL
secureaiml-0.1.3.dist-info/entry_points.txt
secureaiml-0.1.3.dist-info/top_level.txt
secureaiml-0.1.3.dist-info/RECORD
