Metadata-Version: 2.4
Name: secureaiml
Version: 0.1.3
Summary: Enterprise-Ready AI Model Security built on OpenSSF Model Signing
Author-email: Krish <krish.dhar@owasp.org>
License: Apache License
Project-URL: Homepage, https://github.com/OWASP/SecureML
Project-URL: Documentation, https://github.com/OWASP/SecureML/blob/master/secureml/docs/
Project-URL: Repository, https://github.com/OWASP/SecureML
Project-URL: Issues, https://github.com/OWASP/SecureML/issues
Project-URL: Changelog, https://github.com/OWASP/SecureML/blob/master/secureml/CHANGELOG.md
Keywords: machine-learning,security,ai,model-signing,mlops,openssf,sigstore,ml-security,model-security
Classifier: Development Status :: 3 - Alpha
Classifier: Intended Audience :: Developers
Classifier: Intended Audience :: Science/Research
Classifier: License :: OSI Approved :: Apache Software License
Classifier: Programming Language :: Python :: 3
Classifier: Programming Language :: Python :: 3.8
Classifier: Programming Language :: Python :: 3.9
Classifier: Programming Language :: Python :: 3.10
Classifier: Programming Language :: Python :: 3.11
Classifier: Programming Language :: Python :: 3.12
Classifier: Topic :: Security
Classifier: Topic :: Scientific/Engineering :: Artificial Intelligence
Classifier: Topic :: Software Development :: Libraries :: Python Modules
Requires-Python: >=3.8
License-File: LICENSE
Requires-Dist: cryptography>=41.0.0
Requires-Dist: joblib>=1.3.0
Requires-Dist: numpy>=1.20.0
Requires-Dist: pyyaml>=6.0
Requires-Dist: typing-extensions>=4.7.0
Provides-Extra: xgboost
Requires-Dist: xgboost>=2.0.0; extra == "xgboost"
Provides-Extra: pytorch
Requires-Dist: torch>=2.0.0; extra == "pytorch"
Provides-Extra: tensorflow
Requires-Dist: tensorflow>=2.13.0; extra == "tensorflow"
Provides-Extra: sklearn
Requires-Dist: scikit-learn>=1.3.0; extra == "sklearn"
Provides-Extra: lightgbm
Requires-Dist: lightgbm>=4.0.0; extra == "lightgbm"
Provides-Extra: catboost
Requires-Dist: catboost>=1.2.0; extra == "catboost"
Provides-Extra: huggingface
Requires-Dist: transformers>=4.30.0; extra == "huggingface"
Requires-Dist: safetensors>=0.3.0; extra == "huggingface"
Provides-Extra: onnx
Requires-Dist: onnx>=1.14.0; extra == "onnx"
Requires-Dist: onnxruntime>=1.15.0; extra == "onnx"
Provides-Extra: ml-all
Requires-Dist: xgboost>=2.0.0; extra == "ml-all"
Requires-Dist: torch>=2.0.0; extra == "ml-all"
Requires-Dist: scikit-learn>=1.3.0; extra == "ml-all"
Requires-Dist: lightgbm>=4.0.0; extra == "ml-all"
Requires-Dist: transformers>=4.30.0; extra == "ml-all"
Provides-Extra: cli
Requires-Dist: click>=8.1.0; extra == "cli"
Requires-Dist: rich>=13.0.0; extra == "cli"
Provides-Extra: enterprise
Requires-Dist: boto3>=1.28.0; extra == "enterprise"
Requires-Dist: azure-keyvault>=4.2.0; extra == "enterprise"
Requires-Dist: google-cloud-kms>=2.19.0; extra == "enterprise"
Provides-Extra: integrations
Requires-Dist: mlflow>=2.5.0; extra == "integrations"
Requires-Dist: wandb>=0.15.0; extra == "integrations"
Provides-Extra: dev
Requires-Dist: pytest>=7.4.0; extra == "dev"
Requires-Dist: pytest-cov>=4.1.0; extra == "dev"
Requires-Dist: pytest-mock>=3.11.0; extra == "dev"
Requires-Dist: pytest-asyncio>=0.21.0; extra == "dev"
Requires-Dist: black>=23.0.0; extra == "dev"
Requires-Dist: ruff>=0.1.0; extra == "dev"
Requires-Dist: mypy>=1.5.0; extra == "dev"
Requires-Dist: pre-commit>=3.3.0; extra == "dev"
Requires-Dist: ipython>=8.12.0; extra == "dev"
Requires-Dist: build>=0.10.0; extra == "dev"
Requires-Dist: scikit-learn>=1.3.0; extra == "dev"
Provides-Extra: docs
Requires-Dist: mkdocs>=1.5.0; extra == "docs"
Requires-Dist: mkdocs-material>=9.4.0; extra == "docs"
Requires-Dist: mkdocstrings[python]>=0.23.0; extra == "docs"
Provides-Extra: all
Requires-Dist: secureml[cli,dev,docs,enterprise,integrations,ml-all]; extra == "all"
Dynamic: license-file
